neetcode_rpg_by_neon-1.0.0.dist-info/licenses/LICENSE
src/__init__.py
src/main.py
src/config/__init__.py
src/controllers/__init__.py
src/controllers/cli.py
src/models/__init__.py
src/models/problem.py
src/models/progress.py
src/services/__init__.py
src/services/graph_service.py
src/services/problem_service.py
src/services/rpg_service.py
src/utils/__init__.py
src/views/__init__.py
src/views/console.py
neetcode_rpg_by_neon-1.0.0.dist-info/METADATA
neetcode_rpg_by_neon-1.0.0.dist-info/WHEEL
neetcode_rpg_by_neon-1.0.0.dist-info/entry_points.txt
neetcode_rpg_by_neon-1.0.0.dist-info/top_level.txt
neetcode_rpg_by_neon-1.0.0.dist-info/RECORD
