Metadata-Version: 2.4
Name: neetcode-rpg-by-neon
Version: 1.0.0
Summary: 🎮 Transform DSA practice into an addictive RPG adventure! Level up from Coding Seedling to NeetCode Deity.
Author-email: Neon <dmcbaditya@gmail.com>
License: MIT License
Project-URL: Homepage, https://github.com/addynoven/neetcode-rpg
Project-URL: Bug Reports, https://github.com/addynoven/neetcode-rpg/issues
Project-URL: Source Code, https://github.com/addynoven/neetcode-rpg
Project-URL: Documentation, https://github.com/addynoven/neetcode-rpg#readme
Project-URL: Author LinkedIn, https://www.linkedin.com/in/aditya-sahu-34350b193/
Project-URL: Author GitHub, https://github.com/addynoven
Keywords: dsa,algorithms,data-structures,leetcode,neetcode,rpg,gamification,learning,education,cli
Classifier: Development Status :: 5 - Production/Stable
Classifier: Intended Audience :: Developers
Classifier: Intended Audience :: Education
Classifier: Topic :: Education
Classifier: Topic :: Software Development :: Libraries :: Python Modules
Classifier: Topic :: Games/Entertainment :: Role-Playing
Classifier: License :: OSI Approved :: MIT License
Classifier: Programming Language :: Python :: 3
Classifier: Programming Language :: Python :: 3.8
Classifier: Programming Language :: Python :: 3.9
Classifier: Programming Language :: Python :: 3.10
Classifier: Programming Language :: Python :: 3.11
Classifier: Programming Language :: Python :: 3.12
Classifier: Operating System :: OS Independent
Classifier: Environment :: Console
Requires-Python: >=3.8
License-File: LICENSE
Requires-Dist: typer>=0.9.0
Requires-Dist: rich>=13.0.0
Requires-Dist: matplotlib>=3.5.0
Requires-Dist: pillow>=9.0.0
Dynamic: license-file
